pyromaji/__init__.py
pyromaji/romaji.py
pyromaji-0.0.5.dist-info/METADATA
pyromaji-0.0.5.dist-info/WHEEL
pyromaji-0.0.5.dist-info/top_level.txt
pyromaji-0.0.5.dist-info/RECORD
