Metadata-Version: 2.1
Name: pyromaji
Version: 0.0.5
Summary: Romaji to Hiragana conversion library
Home-page: https://github.com/miidas/pyromaji
Author: miidas
License: UNKNOWN
Platform: UNKNOWN
